django_server_testing/__init__.py
django_server_testing/const.py
django_server_testing/error.py
django_server_testing/server.py
django_server_testing/structure.py
django_server_testing/test_server/__init__.py
django_server_testing/test_server/update_tests/__init__.py
django_server_testing/test_server/update_tests/temp_files.data
django_server_testing/tests/__init__.py
django_server_testing/tests/test_httpheaderstorage.py
django_server_testing/tests/test_server.py
django_server_testing/tests/update_tests/__init__.py
django_server_testing-4.0.5.dist-info/METADATA
django_server_testing-4.0.5.dist-info/WHEEL
django_server_testing-4.0.5.dist-info/top_level.txt
django_server_testing-4.0.5.dist-info/RECORD
