Metadata-Version: 2.1
Name: django-server-testing
Version: 4.0.5
Home-page: https://github.com/lum0vi/django_server_testing
Author: SODT
Author-email: svsharygin@icloud.com
Project-URL: GitHub, https://github.com/lum0vi/django_server_testing
Keywords: files speedfiles
Classifier: Programming Language :: Python :: 3.11
Requires-Python: >=3.6
Requires-Dist: requests >=2.25.1
